{"al": {"estado": "rechazada", "sugerencia": null}, "más": {"estado": "rechazada", "sugerencia": null}, "hay": {"estado": "rechazada", "sugerencia": null}, "chiste": {"estado": "rechazada", "sugerencia": null}, "la": {"estado": "rechazada", "sugerencia": null}, "narco": {"estado": "aceptada", "sugerencia": "narcotraficante"}, "mas": {"estado": "aceptada", "sugerencia": "más"}, "asqueroso": {"estado": "aceptada", "sugerencia": "asqueroso"}, "cara": {"estado": "rechazada", "sugerencia": null}, "anda": {"estado": "rechazada", "sugerencia": null}, "mal": {"estado": "rechazada", "sugerencia": null}, "chisme": {"estado": "aceptada", "sugerencia": "chisme"}, "las": {"estado": "rechazada", "sugerencia": null}, "cada": {"estado": "rechazada", "sugerencia": null}, "bla": {"estado": "aceptada", "sugerencia": "bla"}, "ay": {"estado": "rechazada", "sugerencia": null}, "xd": {"estado": "aceptada", "sugerencia": "xd"}, "voto": {"estado": "rechazada", "sugerencia": null}, "alv": {"estado": "aceptada", "sugerencia": "alv"}, "saco": {"estado": "rechazada", "sugerencia": null}, "pleitos": {"estado": "aceptada", "sugerencia": "pleito"}, "payasa": {"estado": "aceptada", "sugerencia": "payaso"}, "mis": {"estado": "rechazada", "sugerencia": null}, "caido": {"estado": "aceptada", "sugerencia": "caído"}, "males": {"estado": "rechazada", "sugerencia": null}, "padres": {"estado": "rechazada", "sugerencia": null}, "x": {"estado": "rechazada", "sugerencia": null}, "gelatinera": {"estado": "aceptada", "sugerencia": "gelatinera"}, "manda": {"estado": "rechazada", "sugerencia": null}, "chino": {"estado": "rechazada", "sugerencia": null}, "zaco": {"estado": "aceptada", "sugerencia": "saco"}, "payasadas": {"estado": "aceptada", "sugerencia": "payasadas"}, "memes": {"estado": "rechazada", "sugerencia": null}, "jodidos": {"estado": "aceptada", "sugerencia": "jodido"}, "jodido": {"estado": "aceptada", "sugerencia": "jodido"}, "tonterías": {"estado": "aceptada", "sugerencia": "tontería"}, "venga": {"estado": "rechazada", "sugerencia": null}, "botarga": {"estado": "aceptada", "sugerencia": "botarga"}, "guajoloteras": {"estado": "aceptada", "sugerencia": "guajolotera"}, "traza": {"estado": "aceptada", "sugerencia": "tranza"}, "ardida": {"estado": "aceptada", "sugerencia": "ardido"}, "vas": {"estado": "rechazada", "sugerencia": null}, "xk": {"estado": "aceptada", "sugerencia": "porque"}, "bandas": {"estado": "aceptada", "sugerencia": "carteles"}, "poca": {"estado": "rechazada", "sugerencia": null}, "gelatinas": {"estado": "aceptada", "sugerencia": "gelatinas"}, "d": {"estado": "aceptada", "sugerencia": "de"}, "de": {"estado": "rechazada", "sugerencia": null}, "y": {"estado": "rechazada", "sugerencia": null}, "a": {"estado": "rechazada", "sugerencia": null}, "1": {"estado": "rechazada", "sugerencia": null}, "q": {"estado": "rechazada", "sugerencia": null}, "dé": {"estado": "aceptada", "sugerencia": "de"}, "ala": {"estado": "aceptada", "sugerencia": "a la"}, "ratas": {"estado": "aceptada", "sugerencia": "ratas"}, "marina": {"estado": "rechazada", "sugerencia": null}, "o": {"estado": "rechazada", "sugerencia": null}, "fifis": {"estado": "aceptada", "sugerencia": "fifi"}, "da": {"estado": "rechazada", "sugerencia": null}, "calo": {"estado": "aceptada", "sugerencia": "enojó"}, "pendeja": {"estado": "aceptada", "sugerencia": "pendejo"}, "madres": {"estado": "aceptada", "sugerencia": "madres"}, "2": {"estado": "rechazada", "sugerencia": null}, "casa": {"estado": "rechazada", "sugerencia": null}, "mes": {"estado": "rechazada", "sugerencia": null}, "u": {"estado": "rechazada", "sugerencia": null}, "mala": {"estado": "rechazada", "sugerencia": null}, "cayo": {"estado": "aceptada", "sugerencia": "cayó"}, "matada": {"estado": "aceptada", "sugerencia": "mamada"}, "6": {"estado": "rechazada", "sugerencia": null}, "caso": {"estado": "rechazada", "sugerencia": null}, "saca": {"estado": "rechazada", "sugerencia": null}, "s": {"estado": "rechazada", "sugerencia": null}, "narcos": {"estado": "aceptada", "sugerencia": "narcotraficante"}, "madrina": {"estado": "aceptada", "sugerencia": "madrina"}, "alza": {"estado": "rechazada", "sugerencia": null}, "roto": {"estado": "rechazada", "sugerencia": null}, "toca": {"estado": "rechazada", "sugerencia": null}, "boca": {"estado": "rechazada", "sugerencia": null}, "barda": {"estado": "rechazada", "sugerencia": null}, "jaladas": {"estado": "aceptada", "sugerencia": "jaladas"}, "loca": {"estado": "aceptada", "sugerencia": "loca"}, "3": {"estado": "rechazada", "sugerencia": null}, "8": {"estado": "rechazada", "sugerencia": null}, "mamá": {"estado": "rechazada", "sugerencia": null}, "cartelones": {"estado": "aceptada", "sugerencia": "cartelones"}, "e": {"estado": "rechazada", "sugerencia": null}, "alas": {"estado": "rechazada", "sugerencia": null}, "b": {"estado": "rechazada", "sugerencia": null}, "c": {"estado": "rechazada", "sugerencia": null}, "9": {"estado": "rechazada", "sugerencia": null}, "botos": {"estado": "aceptada", "sugerencia": "votos"}, "nmms": {"estado": "aceptada", "sugerencia": "mms"}, "pinchi": {"estado": "aceptada", "sugerencia": "pinche"}, "verla": {"estado": "rechazada", "sugerencia": null}, "pierda": {"estado": "rechazada", "sugerencia": null}, "xq": {"estado": "aceptada", "sugerencia": "porque"}, "malo": {"estado": "rechazada", "sugerencia": null}, "4": {"estado": "rechazada", "sugerencia": null}, "5": {"estado": "rechazada", "sugerencia": null}, "votos": {"estado": "rechazada", "sugerencia": null}, "pinches": {"estado": "aceptada", "sugerencia": "pinche"}, "k": {"estado": "aceptada", "sugerencia": "que"}, "boto": {"estado": "aceptada", "sugerencia": "votos"}, "i": {"estado": "aceptada", "sugerencia": "y"}, "r": {"estado": "rechazada", "sugerencia": null}, "si": {"estado": "rechazada", "sugerencia": null}, "mada": {"estado": "aceptada", "sugerencia": "dama"}, "ni": {"estado": "rechazada", "sugerencia": null}, "ud": {"estado": "aceptada", "sugerencia": "usted"}, "mi": {"estado": "rechazada", "sugerencia": null}, "alta": {"estado": "rechazada", "sugerencia": null}, "un": {"estado": "rechazada", "sugerencia": null}, "chícharo": {"estado": "aceptada", "sugerencia": "chicharo"}, "nada": {"estado": "rechazada", "sugerencia": null}, "ata": {"estado": "rechazada", "sugerencia": null}, "salv": {"estado": "aceptada", "sugerencia": "alv"}, "vi": {"estado": "rechazada", "sugerencia": null}, "pada": {"estado": "aceptada", "sugerencia": "para"}, "ir": {"estado": "rechazada", "sugerencia": null}, "alla": {"estado": "aceptada", "sugerencia": "allá"}, "k9": {"estado": "aceptada", "sugerencia": "que"}, "mmi": {"estado": "aceptada", "sugerencia": "mi"}, "ami": {"estado": "aceptada", "sugerencia": "a mi"}, "chairos": {"estado": "aceptada", "sugerencia": "chairo"}, "fifi": {"estado": "aceptada", "sugerencia": "fifi"}, "para": {"estado": "rechazada", "sugerencia": null}, "podido": {"estado": "rechazada", "sugerencia": null}, "asi": {"estado": "aceptada", "sugerencia": "así"}, "maña": {"estado": "rechazada", "sugerencia": null}, "ola": {"estado": "rechazada", "sugerencia": null}, "así": {"estado": "aceptada", "sugerencia": "así"}, "pasa": {"estado": "rechazada", "sugerencia": null}, "uy": {"estado": "rechazada", "sugerencia": null}, "mierda": {"estado": "aceptada", "sugerencia": "mierda"}, "asia": {"estado": "rechazada", "sugerencia": null}, "chicharoo": {"estado": "aceptada", "sugerencia": "chicharo"}, "votarga": {"estado": "aceptada", "sugerencia": "botarga"}, "patas": {"estado": "rechazada", "sugerencia": null}, "ame": {"estado": "rechazada", "sugerencia": null}, "aki": {"estado": "aceptada", "sugerencia": "aquí"}, "ella": {"estado": "rechazada", "sugerencia": null}, "chinguen": {"estado": "aceptada", "sugerencia": "chingue"}, "gelatina": {"estado": "aceptada", "sugerencia": "gelatinas"}, "falla": {"estado": "rechazada", "sugerencia": null}, "pancartitas": {"estado": "aceptada", "sugerencia": "pancartitas"}, "t": {"estado": "rechazada", "sugerencia": null}, "v": {"estado": "rechazada", "sugerencia": null}, "amo": {"estado": "rechazada", "sugerencia": null}, "pleito": {"estado": "aceptada", "sugerencia": "pleito"}, "maya": {"estado": "rechazada", "sugerencia": null}, "asé": {"estado": "aceptada", "sugerencia": "hace"}, "in": {"estado": "rechazada", "sugerencia": null}, "ims": {"estado": "aceptada", "sugerencia": "IMSS"}, "tontería": {"estado": "aceptada", "sugerencia": "tontería"}, "madre": {"estado": "rechazada", "sugerencia": null}, "dama": {"estado": "rechazada", "sugerencia": null}, "dr": {"estado": "rechazada", "sugerencia": null}, "caño": {"estado": "rechazada", "sugerencia": null}, "foto": {"estado": "rechazada", "sugerencia": null}, "payasos": {"estado": "aceptada", "sugerencia": "payaso"}, "chismes": {"estado": "aceptada", "sugerencia": "chisme"}, "casi": {"estado": "rechazada", "sugerencia": null}, "chido": {"estado": "aceptada", "sugerencia": "chido"}, "ctm": {"estado": "aceptada", "sugerencia": "ctm"}, "surrada": {"estado": "aceptada", "sugerencia": "surrada"}, "imss": {"estado": "aceptada", "sugerencia": "IMSS"}, "arguenderas": {"estado": "aceptada", "sugerencia": "arguenderas"}, "ti": {"estado": "rechazada", "sugerencia": null}, "sé": {"estado": "rechazada", "sugerencia": null}, "paga": {"estado": "rechazada", "sugerencia": null}, "m": {"estado": "rechazada", "sugerencia": null}, "it": {"estado": "rechazada", "sugerencia": null}, "aa": {"estado": "aceptada", "sugerencia": "ah"}, "bandos": {"estado": "aceptada", "sugerencia": "facciones"}, "ya": {"estado": "rechazada", "sugerencia": null}, "sa": {"estado": "aceptada", "sugerencia": "sabe"}, "se": {"estado": "rechazada", "sugerencia": null}, "esa": {"estado": "rechazada", "sugerencia": null}, "maman": {"estado": "aceptada", "sugerencia": "mama"}, "ha": {"estado": "rechazada", "sugerencia": null}, "sra": {"estado": "rechazada", "sugerencia": null}, "sea": {"estado": "rechazada", "sugerencia": null}, "su": {"estado": "rechazada", "sugerencia": null}, "ba": {"estado": "aceptada", "sugerencia": "va"}, "va": {"estado": "rechazada", "sugerencia": null}, "bu": {"estado": "aceptada", "sugerencia": "buh"}, "ahi": {"estado": "aceptada", "sugerencia": "ahí"}, "tu": {"estado": "rechazada", "sugerencia": null}, "mms": {"estado": "aceptada", "sugerencia": "mms"}, "ua": {"estado": "aceptada", "sugerencia": "ya"}, "an": {"estado": "aceptada", "sugerencia": "han"}, "en": {"estado": "rechazada", "sugerencia": null}, "bas": {"estado": "aceptada", "sugerencia": "vas"}, "aya": {"estado": "aceptada", "sugerencia": "allá"}, "orita": {"estado": "aceptada", "sugerencia": "ahorita"}, "una": {"estado": "rechazada", "sugerencia": null}, "pan": {"estado": "rechazada", "sugerencia": null}, "ah": {"estado": "rechazada", "sugerencia": null}, "pedos": {"estado": "aceptada", "sugerencia": "pedos"}, "iba": {"estado": "rechazada", "sugerencia": null}, "dan": {"estado": "rechazada", "sugerencia": null}, "han": {"estado": "rechazada", "sugerencia": null}, "usa": {"estado": "rechazada", "sugerencia": null}, "nms": {"estado": "aceptada", "sugerencia": "mms"}, "has": {"estado": "rechazada", "sugerencia": null}, "sí": {"estado": "rechazada", "sugerencia": null}, "pendejadas": {"estado": "aceptada", "sugerencia": "pendejada"}, "bb": {"estado": "rechazada", "sugerencia": null}, "alma": {"estado": "rechazada", "sugerencia": null}, "verda": {"estado": "aceptada", "sugerencia": "verdad"}, "cabo": {"estado": "rechazada", "sugerencia": null}, "0": {"estado": "aceptada", "sugerencia": "wooow"}, "verdad": {"estado": "rechazada", "sugerencia": null}, "ke": {"estado": "aceptada", "sugerencia": "que"}, "ahí": {"estado": "rechazada", "sugerencia": null}, "bka": {"estado": "aceptada", "sugerencia": "la"}, "pi": {"estado": "aceptada", "sugerencia": "pinche"}, "n": {"estado": "rechazada", "sugerencia": null}, "shi": {"estado": "aceptada", "sugerencia": "pinche"}, "pa": {"estado": "rechazada", "sugerencia": null}, "ca": {"estado": "rechazada", "sugerencia": null}, "arguendera": {"estado": "aceptada", "sugerencia": "arguenderas"}, "pri": {"estado": "rechazada", "sugerencia": null}, "tan": {"estado": "rechazada", "sugerencia": null}, "rata": {"estado": "aceptada", "sugerencia": "ratas"}, "chinge": {"estado": "aceptada", "sugerencia": "chingue"}, "chingue": {"estado": "aceptada", "sugerencia": "chingue"}, "van": {"estado": "rechazada", "sugerencia": null}, "bote": {"estado": "aceptada", "sugerencia": "cárcel"}, "vaya": {"estado": "rechazada", "sugerencia": null}, "frita": {"estado": "aceptada", "sugerencia": "frita"}, "cayó": {"estado": "rechazada", "sugerencia": null}, "payasada": {"estado": "aceptada", "sugerencia": "payasadas"}, "_": {"estado": "rechazada", "sugerencia": null}, "vrg": {"estado": "aceptada", "sugerencia": "vrg"}, "40": {"estado": "rechazada", "sugerencia": null}, "caía": {"estado": "rechazada", "sugerencia": null}, "aún": {"estado": "rechazada", "sugerencia": null}, "30": {"estado": "rechazada", "sugerencia": null}, "02": {"estado": "rechazada", "sugerencia": null}, "10": {"estado": "rechazada", "sugerencia": null}, "dl": {"estado": "aceptada", "sugerencia": "del"}, "el": {"estado": "rechazada", "sugerencia": null}, "mamada": {"estado": "aceptada", "sugerencia": "mamada"}, "00": {"estado": "rechazada", "sugerencia": null}, "bola": {"estado": "aceptada", "sugerencia": "grupo"}, "del": {"estado": "rechazada", "sugerencia": null}, "03": {"estado": "rechazada", "sugerencia": null}, "04": {"estado": "rechazada", "sugerencia": null}, "01": {"estado": "rechazada", "sugerencia": null}, "20": {"estado": "rechazada", "sugerencia": null}, "sao": {"estado": "rechazada", "sugerencia": null}, "aula": {"estado": "rechazada", "sugerencia": null}, "80": {"estado": "rechazada", "sugerencia": null}, "bot": {"estado": "aceptada", "sugerencia": "bots"}, "pesos": {"estado": "rechazada", "sugerencia": null}, "ok": {"estado": "aceptada", "sugerencia": "de acuerdo"}, "bate": {"estado": "rechazada", "sugerencia": null}, "pinche": {"estado": "aceptada", "sugerencia": "pinche"}, "pd": {"estado": "aceptada", "sugerencia": "posdata"}, "aun": {"estado": "aceptada", "sugerencia": "aún"}, "4a": {"estado": "aceptada", "sugerencia": "4ta"}, "4t": {"estado": "rechazada", "sugerencia": null}, "pedo": {"estado": "aceptada", "sugerencia": "pedos"}, "allá": {"estado": "aceptada", "sugerencia": "allá"}, "gaby": {"estado": "rechazada", "sugerencia": null}, "oms": {"estado": "rechazada", "sugerencia": null}, "dle": {"estado": "aceptada", "sugerencia": "del"}, "paca": {"estado": "rechazada", "sugerencia": null}, "ps": {"estado": "aceptada", "sugerencia": "pues"}, "bots": {"estado": "aceptada", "sugerencia": "bots"}, "es": {"estado": "rechazada", "sugerencia": null}, "amas": {"estado": "rechazada", "sugerencia": null}, "sr": {"estado": "rechazada", "sugerencia": null}, "fria": {"estado": "rechazada", "sugerencia": null}, "43": {"estado": "rechazada", "sugerencia": null}, "qu": {"estado": "aceptada", "sugerencia": "que"}, "loka": {"estado": "aceptada", "sugerencia": "loca"}, "que": {"estado": "rechazada", "sugerencia": null}, "base": {"estado": "rechazada", "sugerencia": null}, "caja": {"estado": "rechazada", "sugerencia": null}, "man": {"estado": "aceptada", "sugerencia": "hombre"}, "x2": {"estado": "rechazada", "sugerencia": null}, "07": {"estado": "rechazada", "sugerencia": null}, "mams": {"estado": "aceptada", "sugerencia": "mama"}, "él": {"estado": "rechazada", "sugerencia": null}, "vaca": {"estado": "rechazada", "sugerencia": null}, "os": {"estado": "rechazada", "sugerencia": null}, "7": {"estado": "rechazada", "sugerencia": null}, "qué": {"estado": "rechazada", "sugerencia": null}, "uds": {"estado": "aceptada", "sugerencia": "usted"}, "pendejo": {"estado": "aceptada", "sugerencia": "pendejo"}, "cabrán": {"estado": "rechazada", "sugerencia": null}, "asu": {"estado": "rechazada", "sugerencia": null}, "ai": {"estado": "rechazada", "sugerencia": null}, "l": {"estado": "rechazada", "sugerencia": null}, "ad": {"estado": "rechazada", "sugerencia": null}, "chico": {"estado": "rechazada", "sugerencia": null}, "05": {"estado": "rechazada", "sugerencia": null}, "46": {"estado": "rechazada", "sugerencia": null}, "06": {"estado": "rechazada", "sugerencia": null}, "08": {"estado": "rechazada", "sugerencia": null}, "haya": {"estado": "rechazada", "sugerencia": null}, "mano": {"estado": "rechazada", "sugerencia": null}, "vote": {"estado": "rechazada", "sugerencia": null}, "sola": {"estado": "rechazada", "sugerencia": null}, "chingar": {"estado": "aceptada", "sugerencia": "chingar"}, "prd": {"estado": "rechazada", "sugerencia": null}, "ahy": {"estado": "aceptada", "sugerencia": "ahí"}, "z": {"estado": "rechazada", "sugerencia": null}, "manes": {"estado": "aceptada", "sugerencia": "Maynez"}, "maines": {"estado": "aceptada", "sugerencia": "Maynez"}, "maynes": {"estado": "aceptada", "sugerencia": "Maynez"}, "g": {"estado": "aceptada", "sugerencia": "estúpido"}, "dø": {"estado": "rechazada", "sugerencia": null}, "coml": {"estado": "aceptada", "sugerencia": "como"}, "como": {"estado": "rechazada", "sugerencia": null}, "41": {"estado": "rechazada", "sugerencia": null}, "ierda": {"estado": "aceptada", "sugerencia": "mierda"}, "mata": {"estado": "rechazada", "sugerencia": null}, "44": {"estado": "rechazada", "sugerencia": null}, "dél": {"estado": "rechazada", "sugerencia": null}, "mamadas": {"estado": "aceptada", "sugerencia": "mamada"}, "pir": {"estado": "aceptada", "sugerencia": "por"}, "por": {"estado": "rechazada", "sugerencia": null}, "eun": {"estado": "aceptada", "sugerencia": "un"}, "lla": {"estado": "aceptada", "sugerencia": "ya"}, "mmm": {"estado": "rechazada", "sugerencia": null}, "ana": {"estado": "rechazada", "sugerencia": null}, "ow": {"estado": "rechazada", "sugerencia": null}, "pt": {"estado": "rechazada", "sugerencia": null}, "verde": {"estado": "rechazada", "sugerencia": null}, "chingao": {"estado": "aceptada", "sugerencia": "carajo"}, "com": {"estado": "rechazada", "sugerencia": null}, "chingo": {"estado": "aceptada", "sugerencia": "chingo"}, "pvi": {"estado": "rechazada", "sugerencia": null}, "mayo": {"estado": "rechazada", "sugerencia": null}, "p": {"estado": "rechazada", "sugerencia": null}, "callo": {"estado": "aceptada", "sugerencia": "cayó"}, "mamo": {"estado": "aceptada", "sugerencia": "mama"}, "cola": {"estado": "rechazada", "sugerencia": null}, "calla": {"estado": "rechazada", "sugerencia": null}, "meda": {"estado": "aceptada", "sugerencia": "me da"}, "san": {"estado": "rechazada", "sugerencia": null}, "48": {"estado": "rechazada", "sugerencia": null}, "47": {"estado": "rechazada", "sugerencia": null}, "42": {"estado": "rechazada", "sugerencia": null}, "iq": {"estado": "aceptada", "sugerencia": "cerebro"}, "45": {"estado": "rechazada", "sugerencia": null}, "verga": {"estado": "aceptada", "sugerencia": "verga"}, "pendej": {"estado": "aceptada", "sugerencia": "pendejo"}, "mega": {"estado": "aceptada", "sugerencia": "gran"}, "allí": {"estado": "rechazada", "sugerencia": null}, "oí": {"estado": "rechazada", "sugerencia": null}, "par": {"estado": "rechazada", "sugerencia": null}, "manos": {"estado": "rechazada", "sugerencia": null}, "qpd": {"estado": "aceptada", "sugerencia": "que en paz descanse"}, "kk": {"estado": "aceptada", "sugerencia": "caca"}}